pandas_sans_lambdas/__init__.py
pandas_sans_lambdas/_build_helpers.py
pandas_sans_lambdas/helpers.py
pandas_sans_lambdas-0.1.1.dist-info/LICENSE
pandas_sans_lambdas-0.1.1.dist-info/METADATA
pandas_sans_lambdas-0.1.1.dist-info/WHEEL
pandas_sans_lambdas-0.1.1.dist-info/top_level.txt
pandas_sans_lambdas-0.1.1.dist-info/RECORD
