Metadata-Version: 2.1
Name: pandas-sans-lambdas
Version: 0.1.1
Summary: Tools to simplify pandas-based data processing
Author-email: Jake Antmann <jakeantmann@gmail.com>
Maintainer-email: Jake Antmann <jakeantmann@gmail.com>
License: MIT License
Project-URL: homepage, https://github.com/jakeantmann/pandas_sans_lambdas
Project-URL: repository, https://github.com//jakeantmann/pandas_sans_lambdas
Project-URL: releases, https://github.com//jakeantmann/pandas_sans_lambdas/releases
Project-URL: issues, https://github.com/jakeantmann/pandas_sans_lambdas/issues
Project-URL: discussions, https://github.com/jakeantmann/pandas_sans_lambdas/discussions
Keywords: pandas
Classifier: Development Status :: 1 - Planning
Classifier: Environment :: Console
Classifier: Intended Audience :: Developers
Classifier: License :: OSI Approved :: MIT License
Classifier: Operating System :: OS Independent
Classifier: Framework :: Pytest
Classifier: Framework :: tox
Classifier: Framework :: Sphinx
Classifier: Programming Language :: Python
Classifier: Programming Language :: Python :: 3.9
Classifier: Programming Language :: Python :: 3.10
Classifier: Programming Language :: Python :: 3.11
Classifier: Programming Language :: Python :: 3 :: Only
Requires-Python: >=3.6
License-File: LICENSE
Requires-Dist: pandas (>=1.5.0)
Requires-Dist: numpy (>=1.23.4)
Provides-Extra: tests
Requires-Dist: coverage (==6.3.2) ; extra == 'tests'
Requires-Dist: pytest (==7.1.3) ; extra == 'tests'
Requires-Dist: pytest-cov (==3.0.0) ; extra == 'tests'
